dbpool/__init__.py
dbpool/impl.py
dbpool-1.2.1.dist-info/LICENSE
dbpool-1.2.1.dist-info/WHEEL
dbpool-1.2.1.dist-info/METADATA
dbpool-1.2.1.dist-info/RECORD
